deepobs/__init__.py
deepobs/config.py
deepobs/version.py
deepobs/abstract_runner/__init__.py
deepobs/abstract_runner/abstract_runner.py
deepobs/abstract_runner/abstract_runner_utils.py
deepobs/analyzer/__init__.py
deepobs/analyzer/analyze.py
deepobs/analyzer/analyze_utils.py
deepobs/analyzer/shared_utils.py
deepobs/pytorch/__init__.py
deepobs/pytorch/config.py
deepobs/pytorch/datasets/__init__.py
deepobs/pytorch/datasets/cifar10.py
deepobs/pytorch/datasets/cifar100.py
deepobs/pytorch/datasets/dataset.py
deepobs/pytorch/datasets/datasets_utils.py
deepobs/pytorch/datasets/fmnist.py
deepobs/pytorch/datasets/mnist.py
deepobs/pytorch/datasets/quadratic.py
deepobs/pytorch/datasets/svhn.py
deepobs/pytorch/datasets/tolstoi.py
deepobs/pytorch/runners/__init__.py
deepobs/pytorch/runners/runner.py
deepobs/pytorch/runners/runner_utils.py
deepobs/pytorch/testproblems/__init__.py
deepobs/pytorch/testproblems/cifar100_3c3d.py
deepobs/pytorch/testproblems/cifar100_allcnnc.py
deepobs/pytorch/testproblems/cifar10_3c3d.py
deepobs/pytorch/testproblems/fmnist_2c2d.py
deepobs/pytorch/testproblems/fmnist_mlp.py
deepobs/pytorch/testproblems/fmnist_vae.py
deepobs/pytorch/testproblems/mnist_2c2d.py
deepobs/pytorch/testproblems/mnist_logreg.py
deepobs/pytorch/testproblems/mnist_mlp.py
deepobs/pytorch/testproblems/mnist_vae.py
deepobs/pytorch/testproblems/quadratic_deep.py
deepobs/pytorch/testproblems/svhn_wrn164.py
deepobs/pytorch/testproblems/testproblem.py
deepobs/pytorch/testproblems/testproblems_modules.py
deepobs/pytorch/testproblems/testproblems_utils.py
deepobs/scripts/__init__.py
deepobs/scripts/_svhn_preprocess.py
deepobs/scripts/_tolstoi_preprocess.py
deepobs/scripts/deepobs_estimate_runtime.py
deepobs/scripts/deepobs_plot_results.py
deepobs/tensorflow/__init__.py
deepobs/tensorflow/config.py
deepobs/tensorflow/datasets/__init__.py
deepobs/tensorflow/datasets/cifar10.py
deepobs/tensorflow/datasets/cifar100.py
deepobs/tensorflow/datasets/dataset.py
deepobs-1.1.2.dist-info/LICENSE
deepobs-1.1.2.dist-info/METADATA
deepobs-1.1.2.dist-info/WHEEL
deepobs-1.1.2.dist-info/top_level.txt
deepobs-1.1.2.dist-info/RECORD
