Metadata-Version: 2.1
Name: deepobs
Version: 1.1.2
Summary: Deep Learning Optimizer Benchmark Suite
Home-page: UNKNOWN
Author: Frank Schneider, Lukas Balles and Philipp Hennig,
Author-email: frank.schneider@tue.mpg.de
License: MIT
Platform: UNKNOWN
Classifier: Programming Language :: Python :: 3.6
Classifier: Intended Audience :: Developers
Classifier: Intended Audience :: Science/Research
Classifier: License :: OSI Approved :: MIT License
Classifier: Operating System :: OS Independent
Classifier: Topic :: Scientific/Engineering :: Artificial Intelligence
Requires-Dist: argparse
Requires-Dist: numpy
Requires-Dist: pandas
Requires-Dist: matplotlib
Requires-Dist: matplotlib2tikz (==0.6.18)
Requires-Dist: seaborn
